mathhook-0.1.4.dist-info/METADATA
mathhook-0.1.4.dist-info/WHEEL
mathhook/__init__.py
mathhook/mathhook.pyd
mathhook/py.typed
mathhook-0.1.4.dist-info/RECORD
