Metadata-Version: 2.4
Name: mathhook
Version: 0.1.4
Classifier: Development Status :: 4 - Beta
Classifier: Intended Audience :: Education
Classifier: Intended Audience :: Science/Research
Classifier: License :: OSI Approved :: MIT License
Classifier: Programming Language :: Python :: 3
Classifier: Programming Language :: Python :: 3.8
Classifier: Programming Language :: Python :: 3.9
Classifier: Programming Language :: Python :: 3.10
Classifier: Programming Language :: Python :: 3.11
Classifier: Programming Language :: Python :: 3.12
Classifier: Topic :: Scientific/Engineering :: Mathematics
Summary: High-performance educational computer algebra system
Keywords: mathematics,algebra,symbolic,education,calculus
Home-Page: https://github.com/AhmedMashour/mathhook
Author-email: Ahmed Mashhour <mpghknown@gmail.com>
License: MIT OR Apache-2.0
Requires-Python: >=3.8
Project-URL: Homepage, https://github.com/AhmedMashour/mathhook
Project-URL: Repository, https://github.com/AhmedMashour/mathhook
Project-URL: Documentation, https://docs.rs/mathhook
Project-URL: Bug Tracker, https://github.com/AhmedMashour/mathhook/issues
